FullSpeedPythonZhongwenbanFix1/README.md
FullSpeedPythonZhongwenbanFix1/__init__.py
FullSpeedPythonZhongwenbanFix1/__main__.py
FullSpeedPythonZhongwenbanFix1/file.epub
FullSpeedPythonZhongwenbanFix1/index.html
FullSpeedPythonZhongwenbanFix1/css/__init__.py
FullSpeedPythonZhongwenbanFix1/css/annotations.css
FullSpeedPythonZhongwenbanFix1/css/main.css
FullSpeedPythonZhongwenbanFix1/css/normalize.css
FullSpeedPythonZhongwenbanFix1/css/popup.css
FullSpeedPythonZhongwenbanFix1/font/__init__.py
FullSpeedPythonZhongwenbanFix1/font/fontello.eot
FullSpeedPythonZhongwenbanFix1/font/fontello.svg
FullSpeedPythonZhongwenbanFix1/font/fontello.ttf
FullSpeedPythonZhongwenbanFix1/font/fontello.woff
FullSpeedPythonZhongwenbanFix1/img/__init__.py
FullSpeedPythonZhongwenbanFix1/img/annotator-glyph-sprite.png
FullSpeedPythonZhongwenbanFix1/img/annotator-icon-sprite.png
FullSpeedPythonZhongwenbanFix1/img/apple-touch-icon.png
FullSpeedPythonZhongwenbanFix1/img/cancelfullscreen.png
FullSpeedPythonZhongwenbanFix1/img/close.png
FullSpeedPythonZhongwenbanFix1/img/fullscreen.png
FullSpeedPythonZhongwenbanFix1/img/loader.gif
FullSpeedPythonZhongwenbanFix1/img/menu-icon.png
FullSpeedPythonZhongwenbanFix1/img/save.png
FullSpeedPythonZhongwenbanFix1/img/saved.png
FullSpeedPythonZhongwenbanFix1/img/settings-s.png
FullSpeedPythonZhongwenbanFix1/img/settings.png
FullSpeedPythonZhongwenbanFix1/img/star.png
FullSpeedPythonZhongwenbanFix1/js/__init__.py
FullSpeedPythonZhongwenbanFix1/js/epub.js
FullSpeedPythonZhongwenbanFix1/js/epub.min.js
FullSpeedPythonZhongwenbanFix1/js/epub.min.map
FullSpeedPythonZhongwenbanFix1/js/hooks.min.js
FullSpeedPythonZhongwenbanFix1/js/hooks.min.map
FullSpeedPythonZhongwenbanFix1/js/reader.js
FullSpeedPythonZhongwenbanFix1/js/reader.js.map
FullSpeedPythonZhongwenbanFix1/js/reader.min.js
FullSpeedPythonZhongwenbanFix1/js/reader.min.map
FullSpeedPythonZhongwenbanFix1/js/hooks/__init__.py
FullSpeedPythonZhongwenbanFix1/js/hooks/extensions/__init__.py
full_speed_python_zhongwenban_fix1-2025.3.24.1.dist-info/METADATA
full_speed_python_zhongwenban_fix1-2025.3.24.1.dist-info/WHEEL
full_speed_python_zhongwenban_fix1-2025.3.24.1.dist-info/entry_points.txt
full_speed_python_zhongwenban_fix1-2025.3.24.1.dist-info/top_level.txt
full_speed_python_zhongwenban_fix1-2025.3.24.1.dist-info/RECORD
